nyxlbox/__init__.py
nyxlbox/adapters.py
nyxlbox/cli.py
nyxlbox/core.py
nyxlbox/eval.py
nyxlbox/reporting.py
nyxlbox/storage.py
nyxlbox-0.1.1.dist-info/METADATA
nyxlbox-0.1.1.dist-info/WHEEL
nyxlbox-0.1.1.dist-info/entry_points.txt
nyxlbox-0.1.1.dist-info/licenses/LICENSE
nyxlbox-0.1.1.dist-info/RECORD
