Metadata-Version: 2.4
Name: nyxlbox
Version: 0.1.1
Summary: Lightweight LLM experiment runner for prompts, evaluation, YAML configs, and reporting.
Project-URL: Homepage, https://github.com/Nyxar0th/nyxlbox
Project-URL: Repository, https://github.com/Nyxar0th/nyxlbox
Author: Nyxar0th
License: Copyright 2025 Nyxar0th
License-File: LICENSE
Keywords: evaluation,experiments,llm,prompts,reporting,yaml
Classifier: Intended Audience :: Developers
Classifier: License :: OSI Approved :: Apache Software License
Classifier: Programming Language :: Python
Classifier: Programming Language :: Python :: 3
Classifier: Programming Language :: Python :: 3.10
Classifier: Programming Language :: Python :: 3.11
Classifier: Programming Language :: Python :: 3.12
Classifier: Programming Language :: Python :: 3.13
Classifier: Programming Language :: Python :: 3.14
Classifier: Topic :: Scientific/Engineering :: Artificial Intelligence
Classifier: Topic :: Software Development :: Testing
Requires-Python: >=3.10
Requires-Dist: pydantic>=2.0.0
Requires-Dist: pyyaml>=6.0.0
Requires-Dist: typer>=0.9.0
Provides-Extra: dev
Requires-Dist: build>=1.3.0; extra == 'dev'
Requires-Dist: pytest>=9.0.2; extra == 'dev'
